conphar/Pharmacophores.py
conphar/Structures.py
conphar/__init__.py
conphar/bin/README
conphar/bin/pharmitserver
conphar-0.2.0.dist-info/LICENSE
conphar-0.2.0.dist-info/METADATA
conphar-0.2.0.dist-info/WHEEL
conphar-0.2.0.dist-info/top_level.txt
conphar-0.2.0.dist-info/RECORD
