Metadata-Version: 2.1
Name: conphar
Version: 0.2.0
Summary: ConPhar
Author: Angel J. Ruiz-Moreno
Author-email: <angel.j.ruiz.moreno@gmail.com>
Keywords: python,pharmacophore,drugdesign,cheminformatics,chemoinformatics,protein
Classifier: Development Status :: 1 - Planning
Classifier: Intended Audience :: Science/Research
Classifier: License :: OSI Approved :: GNU General Public License v3 (GPLv3)
Classifier: Topic :: Scientific/Engineering :: Bio-Informatics
Classifier: Topic :: Scientific/Engineering :: Chemistry
Classifier: Programming Language :: Python :: 3
Classifier: Operating System :: Unix
License-File: LICENSE
Requires-Dist: pandas
Requires-Dist: plotly
Requires-Dist: numpy
Requires-Dist: matplotlib
Requires-Dist: seaborn
Requires-Dist: pymol
Requires-Dist: scikit-learn
